[
  {
    "id": "c3305586-4dde-4a90-a0bc-4dce2e0c840e",
    "status": "completed",
    "source": "/Volumes/data/download",
    "dest": "/Volumes/data/goodStuff/JapanMovie/{actress}/{num}",
    "source_path": "/Volumes/data/download",
    "dest_path": "/Volumes/data/goodStuff/JapanMovie/{actress}/{num}",
    "task_type": "manual",
    "total": 18,
    "completed": 18,
    "success_count": 18,
    "failed_count": 0,
    "created_at": 1783383424030.783,
    "items": [
      {
        "id": 0,
        "dvdid": "ADN-711",
        "title": "请原谅我……已然沉沦的怜悯之心5",
        "status": "success",
        "message": "刮削成功",
        "reason": "",
        "cover": "/Volumes/data/goodStuff/JapanMovie/武藤あやか/ADN-711-C/[ADN-711-C]-poster.jpg",
        "dest_path": "/Volumes/data/goodStuff/JapanMovie/武藤あやか/ADN-711-C",
        "source_path": "/Volumes/data/download/ADN-711-C.mp4"
      },
      {
        "id": 1,
        "dvdid": "ADN-665",
        "title": "答应继父只要10秒钟就允许他进入后……我们之间的契合度高得惊人，让我立刻达到了高潮 安位薫",
        "status": "success",
        "message": "刮削成功",
        "reason": "",
        "cover": "/Volumes/data/goodStuff/JapanMovie/安位カヲル/ADN-665-C/[ADN-665-C]-poster.jpg",
        "dest_path": "/Volumes/data/goodStuff/JapanMovie/安位カヲル/ADN-665-C",
        "source_path": "/Volumes/data/download/ADN-665-C.mp4"
      },
      {
        "id": 2,
        "dvdid": "NSFS-480",
        "title": "新·赎罪23～为获得宽恕，妻子献出了身体～ 友田彩也香（BOD）",
        "status": "success",
        "message": "刮削成功",
        "reason": "",
        "cover": "/Volumes/data/goodStuff/JapanMovie/友田彩也香/NSFS-480-C/[NSFS-480-C]-poster.jpg",
        "dest_path": "/Volumes/data/goodStuff/JapanMovie/友田彩也香/NSFS-480-C",
        "source_path": "/Volumes/data/download/489155.com@NSFS-480-C.mp4"
      },
      {
        "id": 3,
        "dvdid": "NSFS-433",
        "title": "新·赎罪19：为获得宽恕而献出身心的女子 橘京花（BOD）",
        "status": "success",
        "message": "刮削成功",
        "reason": "",
        "cover": "/Volumes/data/goodStuff/JapanMovie/橘京花/NSFS-433-C/[NSFS-433-C]-poster.jpg",
        "dest_path": "/Volumes/data/goodStuff/JapanMovie/橘京花/NSFS-433-C",
        "source_path": "/Volumes/data/download/489155.com@NSFS-433-C.mp4"
      },
      {
        "id": 4,
        "dvdid": "NMSL-040",
        "title": "爱的代价：出卖身体，沉溺于AV男优的惊人技巧所带来的极致快感之中の美少女",
        "status": "success",
        "message": "刮削成功",
        "reason": "",
        "cover": "/Volumes/data/goodStuff/JapanMovie/依本しおり/NMSL-040-C/[NMSL-040-C]-poster.jpg",
        "dest_path": "/Volumes/data/goodStuff/JapanMovie/依本しおり/NMSL-040-C",
        "source_path": "/Volumes/data/download/NMSL-040-C/489155.com@NMSL-040-C.mp4"
      },
      {
        "id": 5,
        "dvdid": "JUR-477",
        "title": "我把我的肉体玩物——人妻借给你吧。在让她承受10次射精之前绝不能离开，乖乖听话的恶毒暴发户大叔的家访记。",
        "status": "success",
        "message": "刮削成功",
        "reason": "",
        "cover": "/Volumes/data/goodStuff/JapanMovie/神宮寺ナオ/JUR-477-C/[JUR-477-C]-poster.jpg",
        "dest_path": "/Volumes/data/goodStuff/JapanMovie/神宮寺ナオ/JUR-477-C",
        "source_path": "/Volumes/data/download/JUR-477-C/JUR-477-C.mp4"
      },
      {
        "id": 6,
        "dvdid": "JUR-566",
        "title": "“哪怕只有一瞬间也好，请让我进入您体内！！” 由于同情30岁仍处处男状态的侄子，我答应了他人生中的愿望并与他发生了关系。结果我们之间的契合度高得惊人，我甚至多次要求再次进行那种带有射精在内的亲密行为。",
        "status": "success",
        "message": "刮削成功",
        "reason": "",
        "cover": "/Volumes/data/goodStuff/JapanMovie/沖宮那美/JUR-566-C/[JUR-566-C]-poster.jpg",
        "dest_path": "/Volumes/data/goodStuff/JapanMovie/沖宮那美/JUR-566-C",
        "source_path": "/Volumes/data/download/JUR-566-C/JUR-566-C.mp4"
      },
      {
        "id": 7,
        "dvdid": "JUR-680",
        "title": "近距离性爱～与上司之间紧密交织的禁忌之恋～",
        "status": "success",
        "message": "刮削成功",
        "reason": "",
        "cover": "/Volumes/data/goodStuff/JapanMovie/市来まひろ/JUR-680-C/[JUR-680-C]-poster.jpg",
        "dest_path": "/Volumes/data/goodStuff/JapanMovie/市来まひろ/JUR-680-C",
        "source_path": "/Volumes/data/download/JUR-680-C/489155.com@JUR-680-C.mp4"
      },
      {
        "id": 8,
        "dvdid": "JUR-754",
        "title": "“哪怕只有一瞬间也好，请让我进入您体内！！” 由于同情30岁仍处处男状态的侄子，我答应了他的心愿并与他发生了关系。结果我们俩的契合度高得惊人，我甚至多次要求再次进行那种带有射精在内的亲密行为。",
        "status": "success",
        "message": "刮削成功",
        "reason": "",
        "cover": "/Volumes/data/goodStuff/JapanMovie/七海ティナ/JUR-754-C/[JUR-754-C]-poster.jpg",
        "dest_path": "/Volumes/data/goodStuff/JapanMovie/七海ティナ/JUR-754-C",
        "source_path": "/Volumes/data/download/JUR-754-C/489155.com@JUR-754-C.mp4"
      },
      {
        "id": 9,
        "dvdid": "SNOS-227",
        "title": "【FANZA限定】长得这么清秀还成了女新闻主播，这人生简直属于赢家了吧？既然大摇大摆地跑到这种贫民区来采风，就算被那些日薪微薄的低收入者嫉妒甚至强暴，也无可奈何吧。附三田真铃3张写真合集。",
        "status": "success",
        "message": "刮削成功",
        "reason": "",
        "cover": "/Volumes/data/goodStuff/JapanMovie/三田真鈴/SNOS-227-C/[SNOS-227-C]-poster.jpg",
        "dest_path": "/Volumes/data/goodStuff/JapanMovie/三田真鈴/SNOS-227-C",
        "source_path": "/Volumes/data/download/SNOS-227-C/489155.com@SNOS-227-C.mp4"
      },
      {
        "id": 10,
        "dvdid": "ADN-789",
        "title": "结婚四年间从未有过性生活的已婚妇女，在那个夜晚被部长拥入怀中。",
        "status": "success",
        "message": "刮削成功",
        "reason": "",
        "cover": "/Volumes/data/goodStuff/JapanMovie/白峰ミウ/ADN-789-C/[ADN-789-C]-poster.jpg",
        "dest_path": "/Volumes/data/goodStuff/JapanMovie/白峰ミウ/ADN-789-C",
        "source_path": "/Volumes/data/download/ADN-789-C/489155.com@ADN-789-C.mp4"
      },
      {
        "id": 11,
        "dvdid": "START-529",
        "title": "新婚第一年的已婚妇女被变态老色鬼记恨在心……在监视下遭到强行插入。",
        "status": "success",
        "message": "刮削成功",
        "reason": "",
        "cover": "/Volumes/data/goodStuff/JapanMovie/宮島めい/START-529-C/[START-529-C]-poster.jpg",
        "dest_path": "/Volumes/data/goodStuff/JapanMovie/宮島めい/START-529-C",
        "source_path": "/Volumes/data/download/START-529-C/489155.com@START-529-C.mp4"
      },
      {
        "id": 12,
        "dvdid": "JUR-081",
        "title": "裸模NTR：深陷羞耻之中的妻子与上司的震撼出轨录像",
        "status": "success",
        "message": "刮削成功",
        "reason": "",
        "cover": "/Volumes/data/goodStuff/JapanMovie/いち花/JUR-081-C/[JUR-081-C]-poster.jpg",
        "dest_path": "/Volumes/data/goodStuff/JapanMovie/いち花/JUR-081-C",
        "source_path": "/Volumes/data/download/JUR-081-C/489155.com@JUR-081-C.mp4"
      },
      {
        "id": 13,
        "dvdid": "JUR-747",
        "title": "从在学生公寓的管理员直人那里失去童贞的那天起，直到毕业为止，我任由他引导，沉溺于那种直接射精的性行为之中，度过了人生最后的青春时光。",
        "status": "success",
        "message": "刮削成功",
        "reason": "",
        "cover": "/Volumes/data/goodStuff/JapanMovie/神宮寺ナオ/JUR-747-C/[JUR-747-C]-poster.jpg",
        "dest_path": "/Volumes/data/goodStuff/JapanMovie/神宮寺ナオ/JUR-747-C",
        "source_path": "/Volumes/data/download/JUR-747-C/489155.com@JUR-747-C.mp4"
      },
      {
        "id": 14,
        "dvdid": "ADN-784",
        "title": "请原谅我……连心都被你夺走了。",
        "status": "success",
        "message": "刮削成功",
        "reason": "",
        "cover": "/Volumes/data/goodStuff/JapanMovie/北野未奈/ADN-784-U/[ADN-784-U]-poster.jpg",
        "dest_path": "/Volumes/data/goodStuff/JapanMovie/北野未奈/ADN-784-U",
        "source_path": "/Volumes/data/download/489155.com@ADN-784-U.mp4"
      },
      {
        "id": 15,
        "dvdid": "JUR-088",
        "title": "【FANZA独家内容】人妻秘书：充满汗水与亲吻的总裁办公室内射性爱，附久远美绪真实写真及内裤套装",
        "status": "success",
        "message": "刮削成功",
        "reason": "",
        "cover": "/Volumes/data/goodStuff/JapanMovie/久遠美緒/JUR-088-U/[JUR-088-U]-poster.jpg",
        "dest_path": "/Volumes/data/goodStuff/JapanMovie/久遠美緒/JUR-088-U",
        "source_path": "/Volumes/data/download/489155.com@JUR-088-U.mp4"
      },
      {
        "id": 16,
        "dvdid": "DASS-977",
        "title": "【千叶原复仇记】遭人怨恨的学生逐渐玷污了彩月老师的子宫。厚实阴部搭配阴险的挑逗计划。",
        "status": "success",
        "message": "刮削成功",
        "reason": "",
        "cover": "/Volumes/data/goodStuff/JapanMovie/彩月七緒/DASS-977-C/[DASS-977-C]-poster.jpg",
        "dest_path": "/Volumes/data/goodStuff/JapanMovie/彩月七緒/DASS-977-C",
        "source_path": "/Volumes/data/download/489155.com@DASS-977-C.mp4"
      },
      {
        "id": 17,
        "dvdid": "NSFS-485",
        "title": "沦陷为比丈夫还要巨大的阳具……这件事，我无法对您说出口。 佐久松奈（BOD）",
        "status": "success",
        "message": "刮削成功",
        "reason": "",
        "cover": "/Volumes/data/goodStuff/JapanMovie/さくまつな/NSFS-485-C/[NSFS-485-C]-poster.jpg",
        "dest_path": "/Volumes/data/goodStuff/JapanMovie/さくまつな/NSFS-485-C",
        "source_path": "/Volumes/data/download/489155.com@NSFS-485-C.mp4"
      }
    ]
  },
  {
    "id": "2a59c108-b821-44f3-bab3-2c5e84c9df4d",
    "status": "completed",
    "source": "/Volumes/data/download",
    "dest": "/Volumes/data/goodStuff/JapanMovie/{actress}/{num}",
    "source_path": "/Volumes/data/download",
    "dest_path": "/Volumes/data/goodStuff/JapanMovie/{actress}/{num}",
    "task_type": "manual",
    "total": 6,
    "completed": 6,
    "success_count": 6,
    "failed_count": 0,
    "created_at": 1783335222155.8762,
    "items": [
      {
        "id": 0,
        "dvdid": "DASS-963",
        "title": "请不要再在孩子面前这样做了……求您住手吧……。刚成为母亲却失去处子之身，这位新人妈妈遭受了无情的折磨与凌辱，心灵被彻底摧毁。不断的拷问、折磨，简直惨不忍睹。",
        "status": "success",
        "message": "刮削成功",
        "reason": "",
        "cover": "/Volumes/data/goodStuff/JapanMovie/竹内有紀/DASS-963-C/[DASS-963-C]-poster.jpg",
        "dest_path": "/Volumes/data/goodStuff/JapanMovie/竹内有紀/DASS-963-C",
        "source_path": "/Volumes/data/download/489155.com@DASS-963-C.mp4"
      },
      {
        "id": 1,
        "dvdid": "NTR-098",
        "title": "【NTR】那种情绪低落的类型在性爱时泪眼汪汪的，真的好色情啊。男友的怒吼声当作背景音乐，简直绝了。",
        "status": "success",
        "message": "刮削成功",
        "reason": "",
        "cover": "/Volumes/data/goodStuff/JapanMovie/みほ/NTR-098/[NTR-098]-poster.jpg",
        "dest_path": "/Volumes/data/goodStuff/JapanMovie/みほ/NTR-098",
        "source_path": "/Volumes/data/download/348NTR-098/489155.com@348NTR-098.mp4"
      },
      {
        "id": 2,
        "dvdid": "DASS-900",
        "title": "在每天向母亲散发着充满爱意的氛围一个月后，他终于失去了理智，与母亲反复进行了多次亲密行为。",
        "status": "success",
        "message": "刮削成功",
        "reason": "",
        "cover": "/Volumes/data/goodStuff/JapanMovie/大槻ひびき/DASS-900-C/[DASS-900-C]-poster.jpg",
        "dest_path": "/Volumes/data/goodStuff/JapanMovie/大槻ひびき/DASS-900-C",
        "source_path": "/Volumes/data/download/DASS-900-C/489155.com@DASS-900-C.mp4"
      },
      {
        "id": 3,
        "dvdid": "DASS-167",
        "title": "在每天向母亲散发着充满爱意的氛围一个月后，他终于失去了理智，与母亲反复进行了多次亲密行为。",
        "status": "success",
        "message": "刮削成功",
        "reason": "",
        "cover": "/Volumes/data/goodStuff/JapanMovie/橘メアリー/DASS-167-C/[DASS-167-C]-poster.jpg",
        "dest_path": "/Volumes/data/goodStuff/JapanMovie/橘メアリー/DASS-167-C",
        "source_path": "/Volumes/data/download/DASS-167-C/DASS-167-C.mp4"
      },
      {
        "id": 4,
        "dvdid": "START-529",
        "title": "新婚第一年的已婚妇女被变态老色鬼怀恨在心……在监视下遭强行插入",
        "status": "success",
        "message": "刮削成功",
        "reason": "",
        "cover": "/Volumes/data/goodStuff/JapanMovie/宮島めい/START-529-C/[START-529-C]-poster.jpg",
        "dest_path": "/Volumes/data/goodStuff/JapanMovie/宮島めい/START-529-C",
        "source_path": "/Volumes/data/download/489155.com@START-529-C.mp4"
      },
      {
        "id": 5,
        "dvdid": "NMSL-040",
        "title": "爱的代价：出卖身体，沉溺于AV男优的惊人技巧所带来的极致快感之中の美少女",
        "status": "success",
        "message": "刮削成功",
        "reason": "",
        "cover": "/Volumes/data/goodStuff/JapanMovie/依本しおり/NMSL-040-C/[NMSL-040-C]-poster.jpg",
        "dest_path": "/Volumes/data/goodStuff/JapanMovie/依本しおり/NMSL-040-C",
        "source_path": "/Volumes/data/download/489155.com@NMSL-040-C.mp4"
      }
    ]
  },
  {
    "id": "c5c495d8-88a1-4e64-aa47-ed05c873a051",
    "status": "stopped",
    "source": "/Volumes/data/download",
    "dest": "/Volumes/data/goodStuff/JapanMovie/{actress}/{num}",
    "source_path": "/Volumes/data/download",
    "dest_path": "/Volumes/data/goodStuff/JapanMovie/{actress}/{num}",
    "task_type": "manual",
    "total": 5,
    "completed": 4,
    "success_count": 4,
    "failed_count": 0,
    "created_at": 1783259107090.7422,
    "items": [
      {
        "id": 0,
        "dvdid": "DASS-963",
        "title": "请不要再在孩子面前这样做了……求您住手吧……。刚成为母亲却失去处子之身，这位新人妈妈遭受了无情的折磨与凌辱，心灵被彻底摧毁。不断的拷问、折磨，简直惨不忍睹。",
        "status": "success",
        "message": "刮削成功",
        "reason": "",
        "cover": "/Volumes/data/goodStuff/JapanMovie/竹内有紀/DASS-963-C/poster.jpg",
        "dest_path": "/Volumes/data/goodStuff/JapanMovie/竹内有紀/DASS-963-C",
        "source_path": "/Volumes/data/download/DASS-963-C/489155.com@DASS-963-C.mp4"
      },
      {
        "id": 1,
        "dvdid": "DASS-900",
        "title": "在每天向母亲散发着充满爱意的氛围一个月后，他终于失去了理智，与母亲反复进行了多次亲密行为。",
        "status": "success",
        "message": "刮削成功",
        "reason": "",
        "cover": "/Volumes/data/goodStuff/JapanMovie/大槻ひびき/DASS-900-C/poster.jpg",
        "dest_path": "/Volumes/data/goodStuff/JapanMovie/大槻ひびき/DASS-900-C",
        "source_path": "/Volumes/data/download/489155.com@DASS-900-C.mp4"
      },
      {
        "id": 2,
        "dvdid": "DASS-167",
        "title": "在每天向母亲散发着充满爱意的氛围一个月后，他终于失去了理智，与母亲反复进行了多次亲密行为。",
        "status": "success",
        "message": "刮削成功",
        "reason": "",
        "cover": "/Volumes/data/goodStuff/JapanMovie/橘メアリー/DASS-167-C/poster.jpg",
        "dest_path": "/Volumes/data/goodStuff/JapanMovie/橘メアリー/DASS-167-C",
        "source_path": "/Volumes/data/download/DASS-167-C.mp4"
      },
      {
        "id": 3,
        "dvdid": "NTR-098",
        "title": "【NTR】那种情绪低落的类型在性爱时泪眼汪汪的，真的好色情啊。男友的怒吼声当作背景音乐，简直绝了。",
        "status": "success",
        "message": "刮削成功",
        "reason": "",
        "cover": "/Volumes/data/goodStuff/JapanMovie/みほ/NTR-098/poster.jpg",
        "dest_path": "/Volumes/data/goodStuff/JapanMovie/みほ/NTR-098",
        "source_path": "/Volumes/data/download/489155.com@348NTR-098.mp4"
      }
    ]
  },
  {
    "id": "760e52de-e7d0-4f7f-8b6b-6c6d8c9b8ec6",
    "status": "stopped",
    "source": "/Volumes/data/download",
    "dest": "/Volumes/data/goodStuff/JapanMovie/{actress}/{num}",
    "source_path": "/Volumes/data/download",
    "dest_path": "/Volumes/data/goodStuff/JapanMovie/{actress}/{num}",
    "task_type": "manual",
    "total": 6,
    "completed": 1,
    "success_count": 1,
    "failed_count": 0,
    "created_at": 1783256662467.756,
    "items": [
      {
        "id": 0,
        "dvdid": "SAME-222",
        "title": "串刺し轮●NTR：关于同期入职的女友在出差住的旅馆里被众人轮替占有的故事。神木彩",
        "status": "success",
        "message": "刮削成功",
        "reason": "",
        "cover": "/Volumes/data/goodStuff/JapanMovie/月雲よる/SAME-222-C/poster.jpg",
        "dest_path": "/Volumes/data/goodStuff/JapanMovie/月雲よる/SAME-222-C",
        "source_path": "/Volumes/data/download/SAME-222-C/489155.com@SAME-222-C.mp4"
      }
    ]
  },
  {
    "id": "b9983c23-2765-4d2b-8836-44e11d9b11f2",
    "status": "stopped",
    "source": "/Volumes/data/download",
    "dest": "/Volumes/data/goodStuff/JapanMovie/{actress}/{num}",
    "source_path": "/Volumes/data/download",
    "dest_path": "/Volumes/data/goodStuff/JapanMovie/{actress}/{num}",
    "task_type": "manual",
    "total": 6,
    "completed": 1,
    "success_count": 1,
    "failed_count": 0,
    "created_at": 1783255703198.828,
    "items": [
      {
        "id": 0,
        "dvdid": "SAME-222",
        "title": "SAME-222",
        "status": "success",
        "message": "刮削成功",
        "reason": "",
        "cover": "/Volumes/data/goodStuff/JapanMovie/月雲よる/SAME-222-C/poster.jpg",
        "dest_path": "/Volumes/data/goodStuff/JapanMovie/月雲よる/SAME-222-C",
        "source_path": "/Volumes/data/download/489155.com@SAME-222-C.mp4"
      }
    ]
  }
]